clustering_coefficient.py
clustering_coefficient-0.1.1.dist-info/METADATA
clustering_coefficient-0.1.1.dist-info/WHEEL
clustering_coefficient-0.1.1.dist-info/RECORD
