Metadata-Version: 2.1
Name: clustering-coefficient
Version: 0.1.1
Summary: Computes the clustering coefficient of nodes as defined by Watts & Strogatz (in their 1998 paper).
Author: Guy
Author-email: guywiz@gmail.com
Requires-Python: >=3.10,<4.0
Classifier: Programming Language :: Python :: 3
Classifier: Programming Language :: Python :: 3.10
Classifier: Programming Language :: Python :: 3.11
Classifier: Programming Language :: Python :: 3.12
Requires-Dist: tulip-python (>=5.7.2,<6.0.0)
